treesource/__init__.py
treesource/__main__.py
treesource/scan.py
treesource/render/__init__.py
treesource/render/engine.py
treesource/render/formats.py
treesource/render/sorting.py
treesource-0.0.6.dist-info/LICENSE.TXT
treesource-0.0.6.dist-info/METADATA
treesource-0.0.6.dist-info/WHEEL
treesource-0.0.6.dist-info/top_level.txt
treesource-0.0.6.dist-info/RECORD
