Metadata-Version: 2.1
Name: treesource
Version: 0.0.6
Summary: commented source file-trees generator 
Home-page: https://github.com/mpascucci/treesource-doc
Author: Marco Pascucci
Author-email: marpas.paris@gmail.com
License: UNKNOWN
Platform: UNKNOWN
Classifier: Programming Language :: Python
Classifier: License :: OSI Approved :: GNU General Public License v2 (GPLv2)
Classifier: Operating System :: OS Independent
Requires-Dist: anytree
